rmtable.py
rmtable/__init__.py
rmtable/column_standard_v1.2.json
rmtable/column_standard_v1.3.json
rmtable/entries_standard_v1.2.json
rmtable/entries_standard_v1.3.json
rmtable/rmtable.py
RMTable-1.2.1.dist-info/LICENSE
RMTable-1.2.1.dist-info/METADATA
RMTable-1.2.1.dist-info/WHEEL
RMTable-1.2.1.dist-info/top_level.txt
RMTable-1.2.1.dist-info/RECORD
