Metadata-Version: 2.1
Name: RMTable
Version: 1.2.1
Summary: Reading, writing, and manipulating RMTables (radio astronomy Faraday rotation catalogs)
Home-page: https://github.com/CIRADA-Tools/RMTable
Maintainer: Cameron Van Eck
Maintainer-email: cameron.van.eck@utoronto.ca
License: MIT
Classifier: Development Status :: 5 - Production/Stable
Classifier: License :: OSI Approved :: MIT License
Classifier: Programming Language :: Python
Classifier: Programming Language :: Python :: 3
Classifier: Programming Language :: Python :: 3.6
Classifier: Intended Audience :: Science/Research
Classifier: Topic :: Scientific/Engineering :: Astronomy
Requires-Python: >=3.5.0
License-File: LICENSE
Requires-Dist: numpy
Requires-Dist: astropy
